ScrappyDoo/ScrappyDoo.py
ScrappyDoo/__init__.py
ScrappyDoo-0.0.1.6.dist-info/LICENSE
ScrappyDoo-0.0.1.6.dist-info/METADATA
ScrappyDoo-0.0.1.6.dist-info/WHEEL
ScrappyDoo-0.0.1.6.dist-info/top_level.txt
ScrappyDoo-0.0.1.6.dist-info/RECORD
