Metadata-Version: 2.1
Name: ScrappyDoo
Version: 0.0.1.6
Summary: Scrape data from website
Home-page: https://github.com/benknight135/ScrappyDoo
Author: Ben Knight
Author-email: info@bknight.co.uk
License: UNKNOWN
Platform: UNKNOWN
Classifier: Programming Language :: Python :: 3
Classifier: License :: OSI Approved :: MIT License
Classifier: Operating System :: OS Independent
Requires-Python: >=3.6
